{
  "ai_name"      : "Han Solo",

  "title_1"      : "der Schmuggler",
  "title_2"      : "ist solo",
  "title_3"      : "der Hyperraumpilot",
  "title_4"      : "Held der Rebellion",
  "title_5"      : "der Schmuggler",
  "title_6"      : "ist solo",
  "title_7"      : "der Hyperraumpilot",
  "title_8"      : "Held der Rebellion",

  "description"  : "Han Solo ist ein Schmuggler vom Volk der Corellianer, welcher schon früh das mit dem Schmuggeln anfing. Nun reist er mit seinem Schiff, dem Millennium Falken auch in die Wüste und führt aus seinem Schiff (Schmuggel) Operationen durch. Dabei setzt er sowohl getreue Rebellen als auch Schmuggler- Söldner aus allen Teilen der Galaxis ein."
}
